{
  "flags": {},
  "shapes": [
    {
      "label": "Nonpollen",
      "line_color": null,
      "fill_color": null,
      "points": [
        [
          1435.0016784667969,
          242.85035133361816
        ],
        [
          1642.3045349121094,
          442.3609256744385
        ]
      ],
      "shape_type": "rectangle",
      "flags": {}
    },
    {
      "label": "Nonpollen",
      "line_color": null,
      "fill_color": null,
      "points": [
        [
          1237.950210571289,
          1647.3208236694336
        ],
        [
          1551.5646362304688,
          1829.0102005004883
        ]
      ],
      "shape_type": "rectangle",
      "flags": {}
    },
    {
      "label": "Nonpollen",
      "line_color": null,
      "fill_color": null,
      "points": [
        [
          1525.9222412109375,
          345.4632568359375
        ],
        [
          1868.0441284179688,
          605.0759696960449
        ]
      ],
      "shape_type": "rectangle",
      "flags": {}
    }
  ],
  "lineColor": [
    0,
    255,
    0,
    128
  ],
  "fillColor": [
    255,
    0,
    0,
    128
  ],
  "imagePath": "Betula nana Tüte 1_S0000(TR1)_Z0003_C00_M0265.jpg",
  "imageData": null
}