{
  "flags": {},
  "shapes": [
    {
      "label": "Nonpollen",
      "line_color": null,
      "fill_color": null,
      "points": [
        [
          354.96997833251953,
          1732.1019744873047
        ],
        [
          598.908576965332,
          1916.9078063964844
        ]
      ],
      "shape_type": "rectangle",
      "flags": {}
    },
    {
      "label": "Betula",
      "line_color": null,
      "fill_color": null,
      "points": [
        [
          1618.0488586425781,
          237.41372108459473
        ],
        [
          1877.0112609863281,
          455.48632621765137
        ]
      ],
      "shape_type": "rectangle",
      "flags": {}
    },
    {
      "label": "Betula",
      "line_color": null,
      "fill_color": null,
      "points": [
        [
          325.21068572998047,
          568.172492980957
        ],
        [
          578.4967422485352,
          751.1981964111328
        ]
      ],
      "shape_type": "rectangle",
      "flags": {}
    }
  ],
  "lineColor": [
    0,
    255,
    0,
    128
  ],
  "fillColor": [
    255,
    0,
    0,
    128
  ],
  "imagePath": "Betula nana Tüte 1_S0000(TR1)_Z0003_C00_M0176.jpg",
  "imageData": null
}