{
  "flags": {},
  "shapes": [
    {
      "label": "Lycopodium",
      "line_color": null,
      "fill_color": null,
      "points": [
        [
          1987.5302124023438,
          1281.723861694336
        ],
        [
          2268.20068359375,
          1442.0407104492188
        ]
      ],
      "shape_type": "rectangle",
      "flags": {}
    },
    {
      "label": "Nonpollen",
      "line_color": null,
      "fill_color": null,
      "points": [
        [
          478.0835723876953,
          938.748607635498
        ],
        [
          741.0350036621094,
          1187.8590774536133
        ]
      ],
      "shape_type": "rectangle",
      "flags": {}
    }
  ],
  "lineColor": [
    0,
    255,
    0,
    128
  ],
  "fillColor": [
    255,
    0,
    0,
    128
  ],
  "imagePath": "Betula nana Tüte 1_S0000(TR1)_Z0004_C00_M0049.jpg",
  "imageData": null
}