{
  "flags": {},
  "shapes": [
    {
      "label": "Nonpollen",
      "line_color": null,
      "fill_color": null,
      "points": [
        [
          1036.8888854980469,
          851.3885307312012
        ],
        [
          1283.1619262695312,
          1107.2397994995117
        ]
      ],
      "shape_type": "rectangle",
      "flags": {}
    },
    {
      "label": "Nonpollen",
      "line_color": null,
      "fill_color": null,
      "points": [
        [
          1143.3211517333984,
          1152.458267211914
        ],
        [
          1354.8698425292969,
          1346.469955444336
        ]
      ],
      "shape_type": "rectangle",
      "flags": {}
    }
  ],
  "lineColor": [
    0,
    255,
    0,
    128
  ],
  "fillColor": [
    255,
    0,
    0,
    128
  ],
  "imagePath": "Betula nana Tüte 1_S0000(TR1)_Z0004_C00_M0005.jpg",
  "imageData": null
}