{
  "flags": {},
  "shapes": [
    {
      "label": "Nonpollen",
      "line_color": null,
      "fill_color": null,
      "points": [
        [
          1525.2174377441406,
          1545.5187606811523
        ],
        [
          1716.7295837402344,
          1731.0812759399414
        ]
      ],
      "shape_type": "rectangle",
      "flags": {}
    },
    {
      "label": "Betula",
      "line_color": null,
      "fill_color": null,
      "points": [
        [
          1154.813461303711,
          706.0905075073242
        ],
        [
          1392.1072387695312,
          906.1644744873047
        ]
      ],
      "shape_type": "rectangle",
      "flags": {}
    },
    {
      "label": "Betula",
      "line_color": null,
      "fill_color": null,
      "points": [
        [
          2349.622802734375,
          1251.0953521728516
        ],
        [
          2547.8924560546875,
          1459.6636962890625
        ]
      ],
      "shape_type": "rectangle",
      "flags": {}
    },
    {
      "label": "Nonpollen",
      "line_color": null,
      "fill_color": null,
      "points": [
        [
          60.97959518432617,
          1454.6161651611328
        ],
        [
          446.1279296875,
          1724.1529083251953
        ]
      ],
      "shape_type": "rectangle",
      "flags": {}
    }
  ],
  "lineColor": [
    0,
    255,
    0,
    128
  ],
  "fillColor": [
    255,
    0,
    0,
    128
  ],
  "imagePath": "Betula nana Tüte 1_S0000(TR1)_Z0001_C00_M0257.jpg",
  "imageData": null
}