{
  "flags": {},
  "shapes": [
    {
      "label": "Other",
      "line_color": null,
      "fill_color": null,
      "points": [
        [
          2002.8173828125,
          310.36757469177246
        ],
        [
          2241.64306640625,
          533.6576843261719
        ]
      ],
      "shape_type": "rectangle",
      "flags": {}
    },
    {
      "label": "Quercus",
      "line_color": null,
      "fill_color": null,
      "points": [
        [
          2438.2308959960938,
          1228.1713485717773
        ],
        [
          2557.2491455078125,
          1470.2553176879883
        ]
      ],
      "shape_type": "rectangle",
      "flags": {}
    },
    {
      "label": "Betula",
      "line_color": null,
      "fill_color": null,
      "points": [
        [
          1095.1615905761719,
          466.9494152069092
        ],
        [
          1300.9536743164062,
          676.9830322265625
        ]
      ],
      "shape_type": "rectangle",
      "flags": {}
    },
    {
      "label": "Betula",
      "line_color": null,
      "fill_color": null,
      "points": [
        [
          1067.103042602539,
          632.8928375244141
        ],
        [
          1281.1093139648438,
          807.0200729370117
        ]
      ],
      "shape_type": "rectangle",
      "flags": {}
    }
  ],
  "lineColor": [
    0,
    255,
    0,
    128
  ],
  "fillColor": [
    255,
    0,
    0,
    128
  ],
  "imagePath": "Betula nana Tüte 1_S0000(TR1)_Z0002_C00_M0244.jpg",
  "imageData": null
}