{
  "flags": {},
  "shapes": [
    {
      "label": "Nonpollen",
      "line_color": null,
      "fill_color": null,
      "points": [
        [
          2021.8698120117188,
          513.457202911377
        ],
        [
          2245.5474853515625,
          735.9218788146973
        ]
      ],
      "shape_type": "rectangle",
      "flags": {}
    },
    {
      "label": "Nonpollen",
      "line_color": null,
      "fill_color": null,
      "points": [
        [
          1311.1431884765625,
          61.486687660217285
        ],
        [
          1587.244873046875,
          308.2987403869629
        ]
      ],
      "shape_type": "rectangle",
      "flags": {}
    }
  ],
  "lineColor": [
    0,
    255,
    0,
    128
  ],
  "fillColor": [
    255,
    0,
    0,
    128
  ],
  "imagePath": "Betula nana Tüte 1_S0000(TR1)_Z0004_C00_M0024.jpg",
  "imageData": null
}