{
  "flags": {},
  "shapes": [
    {
      "label": "Alnus",
      "line_color": null,
      "fill_color": null,
      "points": [
        [
          1691.9477844238281,
          1412.0630264282227
        ],
        [
          1929.8393249511719,
          1634.1775131225586
        ]
      ],
      "shape_type": "rectangle",
      "flags": {}
    },
    {
      "label": "Nonpollen",
      "line_color": null,
      "fill_color": null,
      "points": [
        [
          895.3033447265625,
          1.3544905185699463
        ],
        [
          1126.1015319824219,
          98.46930027008057
        ]
      ],
      "shape_type": "rectangle",
      "flags": {}
    }
  ],
  "lineColor": [
    0,
    255,
    0,
    128
  ],
  "fillColor": [
    255,
    0,
    0,
    128
  ],
  "imagePath": "Betula nana Tüte 1_S0000(TR1)_Z0004_C00_M0058.jpg",
  "imageData": null
}