{
  "flags": {},
  "shapes": [
    {
      "label": "Pinus",
      "line_color": null,
      "fill_color": null,
      "points": [
        [
          1600.9283447265625,
          1.6958856582641602
        ],
        [
          2079.4915771484375,
          249.8642921447754
        ]
      ],
      "shape_type": "rectangle",
      "flags": {}
    },
    {
      "label": "Nonpollen",
      "line_color": null,
      "fill_color": null,
      "points": [
        [
          3.8790225982666016,
          1156.7595291137695
        ],
        [
          172.5719451904297,
          1713.0018997192383
        ]
      ],
      "shape_type": "rectangle",
      "flags": {}
    }
  ],
  "lineColor": [
    0,
    255,
    0,
    128
  ],
  "fillColor": [
    255,
    0,
    0,
    128
  ],
  "imagePath": "Betula nana Tüte 1_S0000(TR1)_Z0002_C00_M0209.jpg",
  "imageData": null
}