{
  "flags": {},
  "shapes": [
    {
      "label": "Betula",
      "line_color": null,
      "fill_color": null,
      "points": [
        [
          1143.15673828125,
          1296.603126525879
        ],
        [
          1372.0442199707031,
          1526.872901916504
        ]
      ],
      "shape_type": "rectangle",
      "flags": {}
    },
    {
      "label": "Betula",
      "line_color": null,
      "fill_color": null,
      "points": [
        [
          2074.126434326172,
          75.89558601379395
        ],
        [
          2335.552215576172,
          319.8410224914551
        ]
      ],
      "shape_type": "rectangle",
      "flags": {}
    }
  ],
  "lineColor": [
    0,
    255,
    0,
    128
  ],
  "fillColor": [
    255,
    0,
    0,
    128
  ],
  "imagePath": "Betula nana Tüte 1_S0000(TR1)_Z0002_C00_M0235.jpg",
  "imageData": null
}