{
  "flags": {},
  "shapes": [
    {
      "label": "Nonpollen",
      "line_color": null,
      "fill_color": null,
      "points": [
        [
          0.4311227798461914,
          0
        ],
        [
          142.87324905395508,
          147.05377578735352
        ]
      ],
      "shape_type": "rectangle",
      "flags": {}
    }
  ],
  "lineColor": [
    0,
    255,
    0,
    128
  ],
  "fillColor": [
    255,
    0,
    0,
    128
  ],
  "imagePath": "Betula nana Tüte 1_S0000(TR1)_Z0004_C00_M0133.jpg",
  "imageData": null
}