{
  "flags": {},
  "shapes": [
    {
      "label": "Corylus",
      "line_color": null,
      "fill_color": null,
      "points": [
        [
          757.8473663330078,
          1049.860954284668
        ],
        [
          1025.589370727539,
          1283.2240676879883
        ]
      ],
      "shape_type": "rectangle",
      "flags": {}
    },
    {
      "label": "Betula",
      "line_color": null,
      "fill_color": null,
      "points": [
        [
          687.9075622558594,
          394.87664222717285
        ],
        [
          921.5031433105469,
          624.3362045288086
        ]
      ],
      "shape_type": "rectangle",
      "flags": {}
    },
    {
      "label": "Betula",
      "line_color": null,
      "fill_color": null,
      "points": [
        [
          2143.4234619140625,
          1434.4202041625977
        ],
        [
          2353.86474609375,
          1644.3476486206055
        ]
      ],
      "shape_type": "rectangle",
      "flags": {}
    },
    {
      "label": "Nonpollen",
      "line_color": null,
      "fill_color": null,
      "points": [
        [
          23.22035789489746,
          686.3510513305664
        ],
        [
          230.03429412841797,
          942.6901245117188
        ]
      ],
      "shape_type": "rectangle",
      "flags": {}
    }
  ],
  "lineColor": [
    0,
    255,
    0,
    128
  ],
  "fillColor": [
    255,
    0,
    0,
    128
  ],
  "imagePath": "Betula nana Tüte 1_S0000(TR1)_Z0001_C00_M0136.jpg",
  "imageData": null
}