{
  "flags": {},
  "shapes": [
    {
      "label": "Betula",
      "line_color": null,
      "fill_color": null,
      "points": [
        [
          272.85783767700195,
          1471.9523620605469
        ],
        [
          511.1051940917969,
          1667.3421478271484
        ]
      ],
      "shape_type": "rectangle",
      "flags": {}
    },
    {
      "label": "Betula",
      "line_color": null,
      "fill_color": null,
      "points": [
        [
          705.5428314208984,
          1346.0278701782227
        ],
        [
          934.8082733154297,
          1530.1088333129883
        ]
      ],
      "shape_type": "rectangle",
      "flags": {}
    }
  ],
  "lineColor": [
    0,
    255,
    0,
    128
  ],
  "fillColor": [
    255,
    0,
    0,
    128
  ],
  "imagePath": "Betula nana Tüte 1_S0000(TR1)_Z0000_C00_M0175.jpg",
  "imageData": null
}