{
  "flags": {},
  "shapes": [
    {
      "label": "Betula",
      "line_color": null,
      "fill_color": null,
      "points": [
        [
          1949.1758728027344,
          1768.4121322631836
        ],
        [
          2243.679962158203,
          1917.7211380004883
        ]
      ],
      "shape_type": "rectangle",
      "flags": {}
    },
    {
      "label": "Betula",
      "line_color": null,
      "fill_color": null,
      "points": [
        [
          398.3647918701172,
          2.718493938446045
        ],
        [
          651.3193511962891,
          155.72402000427246
        ]
      ],
      "shape_type": "rectangle",
      "flags": {}
    },
    {
      "label": "Nonpollen",
      "line_color": null,
      "fill_color": null,
      "points": [
        [
          1417.2642517089844,
          513.7112617492676
        ],
        [
          1630.3089904785156,
          748.5330390930176
        ]
      ],
      "shape_type": "rectangle",
      "flags": {}
    }
  ],
  "lineColor": [
    0,
    255,
    0,
    128
  ],
  "fillColor": [
    255,
    0,
    0,
    128
  ],
  "imagePath": "Betula nana Tüte 1_S0000(TR1)_Z0001_C00_M0298.jpg",
  "imageData": null
}