{
  "flags": {},
  "shapes": [
    {
      "label": "Betula",
      "line_color": null,
      "fill_color": null,
      "points": [
        [
          12.861776351928711,
          12.26599931716919
        ],
        [
          231.53610229492188,
          203.4773826599121
        ]
      ],
      "shape_type": "rectangle",
      "flags": {}
    },
    {
      "label": "Nonpollen",
      "line_color": null,
      "fill_color": null,
      "points": [
        [
          0.8967208862304688,
          1495.1176071166992
        ],
        [
          113.73385429382324,
          1721.3776016235352
        ]
      ],
      "shape_type": "rectangle",
      "flags": {}
    },
    {
      "label": "Betula",
      "line_color": null,
      "fill_color": null,
      "points": [
        [
          270.0567436218262,
          902.5103187561035
        ],
        [
          506.4091491699219,
          1097.9729461669922
        ]
      ],
      "shape_type": "rectangle",
      "flags": {}
    },
    {
      "label": "Quercus",
      "line_color": null,
      "fill_color": null,
      "points": [
        [
          2417.2695922851562,
          1292.215347290039
        ],
        [
          2550.0674438476562,
          1521.7863464355469
        ]
      ],
      "shape_type": "rectangle",
      "flags": {}
    }
  ],
  "lineColor": [
    0,
    255,
    0,
    128
  ],
  "fillColor": [
    255,
    0,
    0,
    128
  ],
  "imagePath": "Betula nana Tüte 1_S0000(TR1)_Z0001_C00_M0232.jpg",
  "imageData": null
}