{
  "flags": {},
  "shapes": [
    {
      "label": "Corylus",
      "line_color": null,
      "fill_color": null,
      "points": [
        [
          601.6242599487305,
          354.34407234191895
        ],
        [
          881.9249725341797,
          592.2509765625
        ]
      ],
      "shape_type": "rectangle",
      "flags": {}
    },
    {
      "label": "Quercus",
      "line_color": null,
      "fill_color": null,
      "points": [
        [
          383.39759826660156,
          1796.0647201538086
        ],
        [
          736.2905120849609,
          1916.6941452026367
        ]
      ],
      "shape_type": "rectangle",
      "flags": {}
    }
  ],
  "lineColor": [
    0,
    255,
    0,
    128
  ],
  "fillColor": [
    255,
    0,
    0,
    128
  ],
  "imagePath": "Betula nana Tüte 1_S0000(TR1)_Z0002_C00_M0210.jpg",
  "imageData": null
}